jaglion/__init__.py
jaglion/cli.py
jaglion/command/__init__.py
jaglion/command/configs.py
jaglion/command/hosts.py
jaglion/command/secret.py
jaglion/exception/__init__.py
jaglion/model/__init__.py
jaglion/model/host.py
jaglion/model/secret.py
jaglion/model/task.py
jaglion/module/__init__.py
jaglion/module/config.py
jaglion/module/database.py
jaglion/module/encrypt.py
jaglion/module/file_system.py
jaglion/module/logger.py
jaglion/module/output.py
jaglion-0.1.0.dist-info/LICENSE.txt
jaglion-0.1.0.dist-info/METADATA
jaglion-0.1.0.dist-info/WHEEL
jaglion-0.1.0.dist-info/entry_points.txt
jaglion-0.1.0.dist-info/top_level.txt
jaglion-0.1.0.dist-info/RECORD
